lab4/instruction_memory/instruction_memory.v
module instruction_memory ( instruction,addr, clk,write_enable);
	input [6:0] addr;
	input clk, write_enable;
	//input [31:0] write_data;
	output [31:0] instruction;
	
	reg [31:0] internalData [127:0];
	reg [31:0] outData;
	
	integer i;
	
	initial begin
		internalData[0]=1'b0;
		internalData[1]=1'b0;
		internalData[2]=32'b10010001000000000001110000001001;     // [0] ADDI    X9, XZR, #7              I  Rd = X9, Rn = XZR, ALUImm = 7
		internalData[3]=32'b11111000000000000000001001101001;   // [1] STUR    X9,[X19.#0]              D  DTAdr = 0, Rn = X19, Rt = X9, op^2 = 0
		internalData[4]=32'b10010001000000000001010000001010;     // [2] ADDI    X10, XZR, #5             I  Rd = X10, Rn = XZR, ALUImm = 5
		internalData[5]=32'b11111000000000000001001001101010;    // [3] STUR    X10.[X19.#1]             D  DTAdr = 1, Rn = X19, Rt = X10, op^2 = 0
		internalData[6]=32'b10010001000000000000100000001011;     // [4] ADDI    X11, XZR, #2             I  Rd = X11, Rn = XZR, ALUImm = 2
		internalData[7]=32'b11111000000000000010001001101011;    // [5] STUR    X11.[X19.#2]             D  DTAdr = 2, Rn = X19, Rt = X11, op^2 = 0
		internalData[8]=32'b10010001000000000001000000001100;     // [6] ADDI    X12, XZR, #4             I  Rd = X12, Rn = XZR, ALUImm = 4
		internalData[9]=32'b11111000000000000011001001101100;    // [7] STUR    X12.[X19.#3]             D  DTAdr = 3, Rn = X19, Rt = X12, op^2 = 0
		internalData[10]=32'b11111000010000000000001001101001;    // [8] LDUR    X9,  [X19.#0]            D  DTAdr = 0, Rn = X19, Rt = X9, op^2 = 0
		internalData[11]=32'b11111000010000000001001001101010;    // [9] LDUR    X10, [X19.#1]            D  DTAdr = 1, Rn = X19, Rt = X10, op^2 = 0
		internalData[12]=32'b11001011000010100000000100101011;    // [10] SUB     X11, X9, X10            R  Rm = X10, shamt = 0, Rn = X9, Rd = X11
		internalData[13]=32'b10010001000000000000110000001100;     // [11] ADDI    X12, XZR, #3            I  Rd = X12, Rn = XZR, ALUImm = 3
		internalData[14]=32'b11101011000011000000000101100000;    // [12] SUBS    XZR, X11, X12           R  Rm = X12, shamt = 0, Rn = X11, Rd = XZR, FLAG = R[Rn]-R[Rm]
		internalData[15]=32'b01010100000000000000000011100000;      // [13] B.GT    L1                      CB if(FLAG==(Z=0 & N=V) ) PC=PC+CondBranchAddress=PC+(20-13) 
		internalData[16]=32'b11111000010000000010001001101001;    // [14] LDUR    X9, [X19.#2]            D  DTAdr = 2, Rn = X19, Rt = X9, op^2 = 0
		internalData[17]=32'b11010011011000000001010100101001;    // [15] LSL     X9, X9, #5              R  Rm = 0, shamt = 5, Rn = X9 = Rd
		internalData[18]=32'b11111000000000000010001001101001;    // [16] STUR    X9, [X19.#2]            D  DTAdr = 2, Rn = X19, Rt = X9, op^2 = 0
		internalData[19]=32'b10010001000000000001110000001100;     // [17] ADDI    X12, XZR, #7            I  Rd = X12, Rn = XZR, ALUImm = 7
		internalData[20]=32'b11111000000000000011001001101100;    // [18] STUR    X12,[X19.#3]            D  DTAdr = 3, Rn = X19, Rt = X12, op^2 = 0
		internalData[21]=32'b00010100000000000000000000011010;       // [19] B       END
		internalData[22]=32'b10010001000000000001100000001100;     // [20] ADDI    X12, XZR, #6            I  Rd = X12, Rn = XZR, ALUImm = 6
		internalData[23]=32'b11111000000000000010001001101100;    // [21] STUR    X12,[X19.#2]            D  DTAdr = 2, Rn = X19, Rt = X12, op^2 = 0
		internalData[24]=32'b11111000010000000011001001101001;    // [22] LDUR    X9, [X19.#3]            D  DTAdr = 3, Rn = X19, Rt = X9, op^2 = 0
		internalData[25]=32'b11010011011000000000100100101001;    // [23] LSL     X9, X9, #2              R  Rm = 0, shamt = 2, Rn = X9 = Rd
		internalData[26]=32'b11111000000000000011001001101001;    // [24] STUR    X9,[X19.#3]             D  DTAdr = 3, Rn = X19, Rt = X9, op^2 = 0
		for (i=26;i<128; i=i+1) begin
			internalData[i]=i;
		end
	end
	
	//write data at neg edge
	//should make it more stable for writing
	/*always @(negedge clk) begin
		if (write_enable) begin
			internalData[addr]=instruction;
		end
	end*/
	//read data at pos edge
	always @ (posedge clk) begin
		//if (!write_enable) begin
			outData = internalData[addr];
		//end
	end
	
	assign instruction=outData;

endmodule

lab4/instruction_memory/instruction_memory_tb.v
`include "instruction_memory.v"

module instruction_memory_tb();

	wire [6:0] addr;
	wire clk, write_enable;
	//input [31:0] write_data;
	wire [31:0] instruction;

	instruction_memory_Tester inMemTester (instruction,addr, clk,write_enable);
	instruction_memory memory (instruction,addr, clk,write_enable);
	
	initial begin
		$dumpfile ("instruction_memory.vcd");
		$dumpvars (1,memory);
	
	end

endmodule

module instruction_memory_Tester (instruction,addr, clk,write_enable);

	output reg [6:0] addr;
	output reg clk, write_enable;
	//input [31:0] write_data;
	inout wire [31:0] instruction;
	
	reg [31:0] data2;
	assign instruction= (write_enable) ? data2 : 32'bz;
	
	parameter stimDelay=1;
	
	initial begin
		$monitor ("addr:%d data:%h WE:%b clk:%b",addr, instruction,write_enable,clk);
	end
	
	
	integer i;
	initial begin
		#stimDelay; clk=1'b1;
		#stimDelay; clk=1'b0;
		/*for (i=0;i<128;i=i+1) begin
			
			
			
			#stimDelay; clk=1'b1;addr=i;data2=128-i;write_enable=1'b1;
			#stimDelay; clk=1'b0;
		end*/
		#stimDelay; clk=1'b1;
		#stimDelay; clk=1'b0;
		for (i=0;i<128;i=i+1) begin
			
			//write_data=128-i;
			
			#stimDelay; clk=1'b1;addr=i;write_enable=1'b0;
			#stimDelay; clk=1'b0;
		end
	end
endmodule

lab4/instruction_memory/instruction_memory.vcd
$date
	Fri Mar 03 02:36:59 2017
$end
$version
	Icarus Verilog
$end
$timescale
	1s
$end
$scope module instruction_memory_tb $end
$scope module memory $end
$var wire 7 ! addr [6:0] $end
$var wire 1 " clk $end
$var wire 32 # instruction [31:0] $end
$var wire 1 $ write_enable $end
$var reg 32 % outData [31:0] $end
$var integer 32 & i [31:0] $end
$upscope $end
$upscope $end
$enddefinitions $end
#0
$dumpvars
b10000000 &
bx %
x$
bx #
x"
bx !
$end
#1
1"
#2
0"
#3
1"
#4
0"
#5
b10100010001001111101111111101001 #
b10100010001001111101111111101001 %
0$
b0 !
1"
#6
0"
#7
b10010011101010111001011011001001 #
b10010011101010111001011011001001 %
b1 !
1"
#8
0"
#9
b1011001101100001111011111110010 #
b1011001101100001111011111110010 %
b10 !
1"
#10
0"
#11
b1101000010100001010011011010010 #
b1101000010100001010011011010010 %
b11 !
1"
#12
0"
#13
b1111001011101101110101111110011 #
b1111001011101101110101111110011 %
b100 !
1"
#14
0"
#15
b11100010000111100011011011010011 #
b11100010000111100011011011010011 %
b101 !
1"
#16
0"
#17
b101101001010001010001001100 #
b101101001010001010001001100 %
b110 !
1"
#18
0"
#19
b10110110110000110100011100101100 #
b10110110110000110100011100101100 %
b111 !
1"
#20
0"
#21
b1000101111010111001011011001001 #
b1000101111010111001011011001001 %
b1000 !
1"
#22
0"
#23
b11010100100001010011011010010 #
b11010100100001010011011010010 %
b1001 !
1"
#24
0"
#25
b10000000011010010110101110010011 #
b10000000011010010110101110010011 %
b1010 !
1"
#26
0"
#27
b11001101100000101101000001001100 #
b11001101100000101101000001001100 %
b1011 !
1"
#28
0"
#29
b1101010010100101010100111100000 #
b1101010010100101010100111100000 %
b1100 !
1"
#30
0"
#31
b110100101010010101111101100000 #
b110100101010010101111101100000 %
b1101 !
1"
#32
0"
#33
b10010100010111100011011011001001 #
b10010100010111100011011011001001 %
b1110 !
1"
#34
0"
#35
b1111010100010000101111110001001 #
b1111010100010000101111110001001 %
b1111 !
1"
#36
0"
#37
b11100010000111100011011011001001 #
b11100010000111100011011011001001 %
b10000 !
1"
#38
0"
#39
b10100010001001111110000001001100 #
b10100010001001111110000001001100 %
b10001 !
1"
#40
0"
#41
b10110110110000110100011100101100 #
b10110110110000110100011100101100 %
b10010 !
1"
#42
0"
#43
b11110100000000000010101100000010 #
b11110100000000000010101100000010 %
b10011 !
1"
#44
0"
#45
b1001110000110111111110001001100 #
b1001110000110111111110001001100 %
b10100 !
1"
#46
0"
#47
b11100010000111100011011100101100 #
b11100010000111100011011100101100 %
b10101 !
1"
#48
0"
#49
b1101001000000110100011011001001 #
b1101001000000110100011011001001 %
b10110 !
1"
#50
0"
#51
b10011010010011100101001110001001 #
b10011010010011100101001110001001 %
b10111 !
1"
#52
0"
#53
b10110110110000110100011011001001 #
b10110110110000110100011011001001 %
b11000 !
1"
#54
0"
#55
b11001 #
b11001 %
b11001 !
1"
#56
0"
#57
b11010 #
b11010 %
b11010 !
1"
#58
0"
#59
b11011 #
b11011 %
b11011 !
1"
#60
0"
#61
b11100 #
b11100 %
b11100 !
1"
#62
0"
#63
b11101 #
b11101 %
b11101 !
1"
#64
0"
#65
b11110 #
b11110 %
b11110 !
1"
#66
0"
#67
b11111 #
b11111 %
b11111 !
1"
#68
0"
#69
b100000 #
b100000 %
b100000 !
1"
#70
0"
#71
b100001 #
b100001 %
b100001 !
1"
#72
0"
#73
b100010 #
b100010 %
b100010 !
1"
#74
0"
#75
b100011 #
b100011 %
b100011 !
1"
#76
0"
#77
b100100 #
b100100 %
b100100 !
1"
#78
0"
#79
b100101 #
b100101 %
b100101 !
1"
#80
0"
#81
b100110 #
b100110 %
b100110 !
1"
#82
0"
#83
b100111 #
b100111 %
b100111 !
1"
#84
0"
#85
b101000 #
b101000 %
b101000 !
1"
#86
0"
#87
b101001 #
b101001 %
b101001 !
1"
#88
0"
#89
b101010 #
b101010 %
b101010 !
1"
#90
0"
#91
b101011 #
b101011 %
b101011 !
1"
#92
0"
#93
b101100 #
b101100 %
b101100 !
1"
#94
0"
#95
b101101 #
b101101 %
b101101 !
1"
#96
0"
#97
b101110 #
b101110 %
b101110 !
1"
#98
0"
#99
b101111 #
b101111 %
b101111 !
1"
#100
0"
#101
b110000 #
b110000 %
b110000 !
1"
#102
0"
#103
b110001 #
b110001 %
b110001 !
1"
#104
0"
#105
b110010 #
b110010 %
b110010 !
1"
#106
0"
#107
b110011 #
b110011 %
b110011 !
1"
#108
0"
#109
b110100 #
b110100 %
b110100 !
1"
#110
0"
#111
b110101 #
b110101 %
b110101 !
1"
#112
0"
#113
b110110 #
b110110 %
b110110 !
1"
#114
0"
#115
b110111 #
b110111 %
b110111 !
1"
#116
0"
#117
b111000 #
b111000 %
b111000 !
1"
#118
0"
#119
b111001 #
b111001 %
b111001 !
1"
#120
0"
#121
b111010 #
b111010 %
b111010 !
1"
#122
0"
#123
b111011 #
b111011 %
b111011 !
1"
#124
0"
#125
b111100 #
b111100 %
b111100 !
1"
#126
0"
#127
b111101 #
b111101 %
b111101 !
1"
#128
0"
#129
b111110 #
b111110 %
b111110 !
1"
#130
0"
#131
b111111 #
b111111 %
b111111 !
1"
#132
0"
#133
b1000000 #
b1000000 %
b1000000 !
1"
#134
0"
#135
b1000001 #
b1000001 %
b1000001 !
1"
#136
0"
#137
b1000010 #
b1000010 %
b1000010 !
1"
#138
0"
#139
b1000011 #
b1000011 %
b1000011 !
1"
#140
0"
#141
b1000100 #
b1000100 %
b1000100 !
1"
#142
0"
#143
b1000101 #
b1000101 %
b1000101 !
1"
#144
0"
#145
b1000110 #
b1000110 %
b1000110 !
1"
#146
0"
#147
b1000111 #
b1000111 %
b1000111 !
1"
#148
0"
#149
b1001000 #
b1001000 %
b1001000 !
1"
#150
0"
#151
b1001001 #
b1001001 %
b1001001 !
1"
#152
0"
#153
b1001010 #
b1001010 %
b1001010 !
1"
#154
0"
#155
b1001011 #
b1001011 %
b1001011 !
1"
#156
0"
#157
b1001100 #
b1001100 %
b1001100 !
1"
#158
0"
#159
b1001101 #
b1001101 %
b1001101 !
1"
#160
0"
#161
b1001110 #
b1001110 %
b1001110 !
1"
#162
0"
#163
b1001111 #
b1001111 %
b1001111 !
1"
#164
0"
#165
b1010000 #
b1010000 %
b1010000 !
1"
#166
0"
#167
b1010001 #
b1010001 %
b1010001 !
1"
#168
0"
#169
b1010010 #
b1010010 %
b1010010 !
1"
#170
0"
#171
b1010011 #
b1010011 %
b1010011 !
1"
#172
0"
#173
b1010100 #
b1010100 %
b1010100 !
1"
#174
0"
#175
b1010101 #
b1010101 %
b1010101 !
1"
#176
0"
#177
b1010110 #
b1010110 %
b1010110 !
1"
#178
0"
#179
b1010111 #
b1010111 %
b1010111 !
1"
#180
0"
#181
b1011000 #
b1011000 %
b1011000 !
1"
#182
0"
#183
b1011001 #
b1011001 %
b1011001 !
1"
#184
0"
#185
b1011010 #
b1011010 %
b1011010 !
1"
#186
0"
#187
b1011011 #
b1011011 %
b1011011 !
1"
#188
0"
#189
b1011100 #
b1011100 %
b1011100 !
1"
#190
0"
#191
b1011101 #
b1011101 %
b1011101 !
1"
#192
0"
#193
b1011110 #
b1011110 %
b1011110 !
1"
#194
0"
#195
b1011111 #
b1011111 %
b1011111 !
1"
#196
0"
#197
b1100000 #
b1100000 %
b1100000 !
1"
#198
0"
#199
b1100001 #
b1100001 %
b1100001 !
1"
#200
0"
#201
b1100010 #
b1100010 %
b1100010 !
1"
#202
0"
#203
b1100011 #
b1100011 %
b1100011 !
1"
#204
0"
#205
b1100100 #
b1100100 %
b1100100 !
1"
#206
0"
#207
b1100101 #
b1100101 %
b1100101 !
1"
#208
0"
#209
b1100110 #
b1100110 %
b1100110 !
1"
#210
0"
#211
b1100111 #
b1100111 %
b1100111 !
1"
#212
0"
#213
b1101000 #
b1101000 %
b1101000 !
1"
#214
0"
#215
b1101001 #
b1101001 %
b1101001 !
1"
#216
0"
#217
b1101010 #
b1101010 %
b1101010 !
1"
#218
0"
#219
b1101011 #
b1101011 %
b1101011 !
1"
#220
0"
#221
b1101100 #
b1101100 %
b1101100 !
1"
#222
0"
#223
b1101101 #
b1101101 %
b1101101 !
1"
#224
0"
#225
b1101110 #
b1101110 %
b1101110 !
1"
#226
0"
#227
b1101111 #
b1101111 %
b1101111 !
1"
#228
0"
#229
b1110000 #
b1110000 %
b1110000 !
1"
#230
0"
#231
b1110001 #
b1110001 %
b1110001 !
1"
#232
0"
#233
b1110010 #
b1110010 %
b1110010 !
1"
#234
0"
#235
b1110011 #
b1110011 %
b1110011 !
1"
#236
0"
#237
b1110100 #
b1110100 %
b1110100 !
1"
#238
0"
#239
b1110101 #
b1110101 %
b1110101 !
1"
#240
0"
#241
b1110110 #
b1110110 %
b1110110 !
1"
#242
0"
#243
b1110111 #
b1110111 %
b1110111 !
1"
#244
0"
#245
b1111000 #
b1111000 %
b1111000 !
1"
#246
0"
#247
b1111001 #
b1111001 %
b1111001 !
1"
#248
0"
#249
b1111010 #
b1111010 %
b1111010 !
1"
#250
0"
#251
b1111011 #
b1111011 %
b1111011 !
1"
#252
0"
#253
b1111100 #
b1111100 %
b1111100 !
1"
#254
0"
#255
b1111101 #
b1111101 %
b1111101 !
1"
#256
0"
#257
b1111110 #
b1111110 %
b1111110 !
1"
#258
0"
#259
b1111111 #
b1111111 %
b1111111 !
1"
