lab4/integration/instruction_memory.v
module instruction_memory ( instruction,addr, clk,write_enable);
	input [6:0] addr;
	input clk, write_enable;
	//input [31:0] write_data;
	inout [31:0] instruction;
	
	reg [31:0] internalData [127:0];
	reg [31:0] outData;
	
	//write data at neg edge
	//should make it more stable for writing
	always @(negedge clk) begin
		if (write_enable) begin
			internalData[addr]=instruction;
		end
	end
	//read data at pos edge
	always @ (posedge clk) begin
		if (!write_enable) begin
			outData = internalData[addr];
		end
	end
	
	assign instruction=(!write_enable) ? outData:32'bZ;

endmodule

lab4/instruction_memory/instruction_memory_tb.v
`include "instruction_memory.v"

module instruction_memory_tb();

	wire [6:0] addr;
	wire clk, write_enable;
	//input [31:0] write_data;
	wire [31:0] instruction;

	instruction_memory_Tester inMemTester (instruction,addr, clk,write_enable);
	instruction_memory memory (instruction,addr, clk,write_enable);
	
	initial begin
		$dumpfile ("instruction_memory.vcd");
		$dumpvars (1,memory);
	
	end

endmodule

module instruction_memory_Tester (instruction,addr, clk,write_enable);

	output reg [6:0] addr;
	output reg clk, write_enable;
	//input [31:0] write_data;
	inout wire [31:0] instruction;
	
	reg [31:0] data2;
	assign instruction= (write_enable) ? data2 : 32'bz;
	
	parameter stimDelay=1;
	
	initial begin
		$monitor ("addr:%d data:%h WE:%b clk:%b",addr, instruction,write_enable,clk);
	end
	
	
	integer i;
	initial begin
		#stimDelay; clk=1'b1;
		#stimDelay; clk=1'b0;
		for (i=0;i<128;i=i+1) begin
			
			
			
			#stimDelay; clk=1'b1;addr=i;data2=128-i;write_enable=1'b1;
			#stimDelay; clk=1'b0;
		end
		#stimDelay; clk=1'b1;
		#stimDelay; clk=1'b0;
		for (i=0;i<128;i=i+1) begin
			
			//write_data=128-i;
			
			#stimDelay; clk=1'b1;addr=i;write_enable=1'b0;
			#stimDelay; clk=1'b0;
		end
	end
endmodule

lab4/instruction_memory/instruction_memory.vcd
$date
	Thu Mar 02 18:32:10 2017
$end
$version
	Icarus Verilog
$end
$timescale
	1s
$end
$scope module instruction_memory_tb $end
$scope module memory $end
$var wire 7 ! addr [6:0] $end
$var wire 1 " clk $end
$var wire 32 # instruction [31:0] $end
$var wire 1 $ write_enable $end
$var reg 32 % outData [31:0] $end
$upscope $end
$upscope $end
$enddefinitions $end
#0
$dumpvars
bx %
x$
bx #
x"
bx !
$end
#1
1"
#2
0"
#3
b10000000 #
1$
b0 !
1"
#4
0"
#5
b1111111 #
b1 !
1"
#6
0"
#7
b1111110 #
b10 !
1"
#8
0"
#9
b1111101 #
b11 !
1"
#10
0"
#11
b1111100 #
b100 !
1"
#12
0"
#13
b1111011 #
b101 !
1"
#14
0"
#15
b1111010 #
b110 !
1"
#16
0"
#17
b1111001 #
b111 !
1"
#18
0"
#19
b1111000 #
b1000 !
1"
#20
0"
#21
b1110111 #
b1001 !
1"
#22
0"
#23
b1110110 #
b1010 !
1"
#24
0"
#25
b1110101 #
b1011 !
1"
#26
0"
#27
b1110100 #
b1100 !
1"
#28
0"
#29
b1110011 #
b1101 !
1"
#30
0"
#31
b1110010 #
b1110 !
1"
#32
0"
#33
b1110001 #
b1111 !
1"
#34
0"
#35
b1110000 #
b10000 !
1"
#36
0"
#37
b1101111 #
b10001 !
1"
#38
0"
#39
b1101110 #
b10010 !
1"
#40
0"
#41
b1101101 #
b10011 !
1"
#42
0"
#43
b1101100 #
b10100 !
1"
#44
0"
#45
b1101011 #
b10101 !
1"
#46
0"
#47
b1101010 #
b10110 !
1"
#48
0"
#49
b1101001 #
b10111 !
1"
#50
0"
#51
b1101000 #
b11000 !
1"
#52
0"
#53
b1100111 #
b11001 !
1"
#54
0"
#55
b1100110 #
b11010 !
1"
#56
0"
#57
b1100101 #
b11011 !
1"
#58
0"
#59
b1100100 #
b11100 !
1"
#60
0"
#61
b1100011 #
b11101 !
1"
#62
0"
#63
b1100010 #
b11110 !
1"
#64
0"
#65
b1100001 #
b11111 !
1"
#66
0"
#67
b1100000 #
b100000 !
1"
#68
0"
#69
b1011111 #
b100001 !
1"
#70
0"
#71
b1011110 #
b100010 !
1"
#72
0"
#73
b1011101 #
b100011 !
1"
#74
0"
#75
b1011100 #
b100100 !
1"
#76
0"
#77
b1011011 #
b100101 !
1"
#78
0"
#79
b1011010 #
b100110 !
1"
#80
0"
#81
b1011001 #
b100111 !
1"
#82
0"
#83
b1011000 #
b101000 !
1"
#84
0"
#85
b1010111 #
b101001 !
1"
#86
0"
#87
b1010110 #
b101010 !
1"
#88
0"
#89
b1010101 #
b101011 !
1"
#90
0"
#91
b1010100 #
b101100 !
1"
#92
0"
#93
b1010011 #
b101101 !
1"
#94
0"
#95
b1010010 #
b101110 !
1"
#96
0"
#97
b1010001 #
b101111 !
1"
#98
0"
#99
b1010000 #
b110000 !
1"
#100
0"
#101
b1001111 #
b110001 !
1"
#102
0"
#103
b1001110 #
b110010 !
1"
#104
0"
#105
b1001101 #
b110011 !
1"
#106
0"
#107
b1001100 #
b110100 !
1"
#108
0"
#109
b1001011 #
b110101 !
1"
#110
0"
#111
b1001010 #
b110110 !
1"
#112
0"
#113
b1001001 #
b110111 !
1"
#114
0"
#115
b1001000 #
b111000 !
1"
#116
0"
#117
b1000111 #
b111001 !
1"
#118
0"
#119
b1000110 #
b111010 !
1"
#120
0"
#121
b1000101 #
b111011 !
1"
#122
0"
#123
b1000100 #
b111100 !
1"
#124
0"
#125
b1000011 #
b111101 !
1"
#126
0"
#127
b1000010 #
b111110 !
1"
#128
0"
#129
b1000001 #
b111111 !
1"
#130
0"
#131
b1000000 #
b1000000 !
1"
#132
0"
#133
b111111 #
b1000001 !
1"
#134
0"
#135
b111110 #
b1000010 !
1"
#136
0"
#137
b111101 #
b1000011 !
1"
#138
0"
#139
b111100 #
b1000100 !
1"
#140
0"
#141
b111011 #
b1000101 !
1"
#142
0"
#143
b111010 #
b1000110 !
1"
#144
0"
#145
b111001 #
b1000111 !
1"
#146
0"
#147
b111000 #
b1001000 !
1"
#148
0"
#149
b110111 #
b1001001 !
1"
#150
0"
#151
b110110 #
b1001010 !
1"
#152
0"
#153
b110101 #
b1001011 !
1"
#154
0"
#155
b110100 #
b1001100 !
1"
#156
0"
#157
b110011 #
b1001101 !
1"
#158
0"
#159
b110010 #
b1001110 !
1"
#160
0"
#161
b110001 #
b1001111 !
1"
#162
0"
#163
b110000 #
b1010000 !
1"
#164
0"
#165
b101111 #
b1010001 !
1"
#166
0"
#167
b101110 #
b1010010 !
1"
#168
0"
#169
b101101 #
b1010011 !
1"
#170
0"
#171
b101100 #
b1010100 !
1"
#172
0"
#173
b101011 #
b1010101 !
1"
#174
0"
#175
b101010 #
b1010110 !
1"
#176
0"
#177
b101001 #
b1010111 !
1"
#178
0"
#179
b101000 #
b1011000 !
1"
#180
0"
#181
b100111 #
b1011001 !
1"
#182
0"
#183
b100110 #
b1011010 !
1"
#184
0"
#185
b100101 #
b1011011 !
1"
#186
0"
#187
b100100 #
b1011100 !
1"
#188
0"
#189
b100011 #
b1011101 !
1"
#190
0"
#191
b100010 #
b1011110 !
1"
#192
0"
#193
b100001 #
b1011111 !
1"
#194
0"
#195
b100000 #
b1100000 !
1"
#196
0"
#197
b11111 #
b1100001 !
1"
#198
0"
#199
b11110 #
b1100010 !
1"
#200
0"
#201
b11101 #
b1100011 !
1"
#202
0"
#203
b11100 #
b1100100 !
1"
#204
0"
#205
b11011 #
b1100101 !
1"
#206
0"
#207
b11010 #
b1100110 !
1"
#208
0"
#209
b11001 #
b1100111 !
1"
#210
0"
#211
b11000 #
b1101000 !
1"
#212
0"
#213
b10111 #
b1101001 !
1"
#214
0"
#215
b10110 #
b1101010 !
1"
#216
0"
#217
b10101 #
b1101011 !
1"
#218
0"
#219
b10100 #
b1101100 !
1"
#220
0"
#221
b10011 #
b1101101 !
1"
#222
0"
#223
b10010 #
b1101110 !
1"
#224
0"
#225
b10001 #
b1101111 !
1"
#226
0"
#227
b10000 #
b1110000 !
1"
#228
0"
#229
b1111 #
b1110001 !
1"
#230
0"
#231
b1110 #
b1110010 !
1"
#232
0"
#233
b1101 #
b1110011 !
1"
#234
0"
#235
b1100 #
b1110100 !
1"
#236
0"
#237
b1011 #
b1110101 !
1"
#238
0"
#239
b1010 #
b1110110 !
1"
#240
0"
#241
b1001 #
b1110111 !
1"
#242
0"
#243
b1000 #
b1111000 !
1"
#244
0"
#245
b111 #
b1111001 !
1"
#246
0"
#247
b110 #
b1111010 !
1"
#248
0"
#249
b101 #
b1111011 !
1"
#250
0"
#251
b100 #
b1111100 !
1"
#252
0"
#253
b11 #
b1111101 !
1"
#254
0"
#255
b10 #
b1111110 !
1"
#256
0"
#257
b1 #
b1111111 !
1"
#258
0"
#259
1"
#260
0"
#261
b10000000 #
b10000000 %
0$
b0 !
1"
#262
0"
#263
b1111111 #
b1111111 %
b1 !
1"
#264
0"
#265
b1111110 #
b1111110 %
b10 !
1"
#266
0"
#267
b1111101 #
b1111101 %
b11 !
1"
#268
0"
#269
b1111100 #
b1111100 %
b100 !
1"
#270
0"
#271
b1111011 #
b1111011 %
b101 !
1"
#272
0"
#273
b1111010 #
b1111010 %
b110 !
1"
#274
0"
#275
b1111001 #
b1111001 %
b111 !
1"
#276
0"
#277
b1111000 #
b1111000 %
b1000 !
1"
#278
0"
#279
b1110111 #
b1110111 %
b1001 !
1"
#280
0"
#281
b1110110 #
b1110110 %
b1010 !
1"
#282
0"
#283
b1110101 #
b1110101 %
b1011 !
1"
#284
0"
#285
b1110100 #
b1110100 %
b1100 !
1"
#286
0"
#287
b1110011 #
b1110011 %
b1101 !
1"
#288
0"
#289
b1110010 #
b1110010 %
b1110 !
1"
#290
0"
#291
b1110001 #
b1110001 %
b1111 !
1"
#292
0"
#293
b1110000 #
b1110000 %
b10000 !
1"
#294
0"
#295
b1101111 #
b1101111 %
b10001 !
1"
#296
0"
#297
b1101110 #
b1101110 %
b10010 !
1"
#298
0"
#299
b1101101 #
b1101101 %
b10011 !
1"
#300
0"
#301
b1101100 #
b1101100 %
b10100 !
1"
#302
0"
#303
b1101011 #
b1101011 %
b10101 !
1"
#304
0"
#305
b1101010 #
b1101010 %
b10110 !
1"
#306
0"
#307
b1101001 #
b1101001 %
b10111 !
1"
#308
0"
#309
b1101000 #
b1101000 %
b11000 !
1"
#310
0"
#311
b1100111 #
b1100111 %
b11001 !
1"
#312
0"
#313
b1100110 #
b1100110 %
b11010 !
1"
#314
0"
#315
b1100101 #
b1100101 %
b11011 !
1"
#316
0"
#317
b1100100 #
b1100100 %
b11100 !
1"
#318
0"
#319
b1100011 #
b1100011 %
b11101 !
1"
#320
0"
#321
b1100010 #
b1100010 %
b11110 !
1"
#322
0"
#323
b1100001 #
b1100001 %
b11111 !
1"
#324
0"
#325
b1100000 #
b1100000 %
b100000 !
1"
#326
0"
#327
b1011111 #
b1011111 %
b100001 !
1"
#328
0"
#329
b1011110 #
b1011110 %
b100010 !
1"
#330
0"
#331
b1011101 #
b1011101 %
b100011 !
1"
#332
0"
#333
b1011100 #
b1011100 %
b100100 !
1"
#334
0"
#335
b1011011 #
b1011011 %
b100101 !
1"
#336
0"
#337
b1011010 #
b1011010 %
b100110 !
1"
#338
0"
#339
b1011001 #
b1011001 %
b100111 !
1"
#340
0"
#341
b1011000 #
b1011000 %
b101000 !
1"
#342
0"
#343
b1010111 #
b1010111 %
b101001 !
1"
#344
0"
#345
b1010110 #
b1010110 %
b101010 !
1"
#346
0"
#347
b1010101 #
b1010101 %
b101011 !
1"
#348
0"
#349
b1010100 #
b1010100 %
b101100 !
1"
#350
0"
#351
b1010011 #
b1010011 %
b101101 !
1"
#352
0"
#353
b1010010 #
b1010010 %
b101110 !
1"
#354
0"
#355
b1010001 #
b1010001 %
b101111 !
1"
#356
0"
#357
b1010000 #
b1010000 %
b110000 !
1"
#358
0"
#359
b1001111 #
b1001111 %
b110001 !
1"
#360
0"
#361
b1001110 #
b1001110 %
b110010 !
1"
#362
0"
#363
b1001101 #
b1001101 %
b110011 !
1"
#364
0"
#365
b1001100 #
b1001100 %
b110100 !
1"
#366
0"
#367
b1001011 #
b1001011 %
b110101 !
1"
#368
0"
#369
b1001010 #
b1001010 %
b110110 !
1"
#370
0"
#371
b1001001 #
b1001001 %
b110111 !
1"
#372
0"
#373
b1001000 #
b1001000 %
b111000 !
1"
#374
0"
#375
b1000111 #
b1000111 %
b111001 !
1"
#376
0"
#377
b1000110 #
b1000110 %
b111010 !
1"
#378
0"
#379
b1000101 #
b1000101 %
b111011 !
1"
#380
0"
#381
b1000100 #
b1000100 %
b111100 !
1"
#382
0"
#383
b1000011 #
b1000011 %
b111101 !
1"
#384
0"
#385
b1000010 #
b1000010 %
b111110 !
1"
#386
0"
#387
b1000001 #
b1000001 %
b111111 !
1"
#388
0"
#389
b1000000 #
b1000000 %
b1000000 !
1"
#390
0"
#391
b111111 #
b111111 %
b1000001 !
1"
#392
0"
#393
b111110 #
b111110 %
b1000010 !
1"
#394
0"
#395
b111101 #
b111101 %
b1000011 !
1"
#396
0"
#397
b111100 #
b111100 %
b1000100 !
1"
#398
0"
#399
b111011 #
b111011 %
b1000101 !
1"
#400
0"
#401
b111010 #
b111010 %
b1000110 !
1"
#402
0"
#403
b111001 #
b111001 %
b1000111 !
1"
#404
0"
#405
b111000 #
b111000 %
b1001000 !
1"
#406
0"
#407
b110111 #
b110111 %
b1001001 !
1"
#408
0"
#409
b110110 #
b110110 %
b1001010 !
1"
#410
0"
#411
b110101 #
b110101 %
b1001011 !
1"
#412
0"
#413
b110100 #
b110100 %
b1001100 !
1"
#414
0"
#415
b110011 #
b110011 %
b1001101 !
1"
#416
0"
#417
b110010 #
b110010 %
b1001110 !
1"
#418
0"
#419
b110001 #
b110001 %
b1001111 !
1"
#420
0"
#421
b110000 #
b110000 %
b1010000 !
1"
#422
0"
#423
b101111 #
b101111 %
b1010001 !
1"
#424
0"
#425
b101110 #
b101110 %
b1010010 !
1"
#426
0"
#427
b101101 #
b101101 %
b1010011 !
1"
#428
0"
#429
b101100 #
b101100 %
b1010100 !
1"
#430
0"
#431
b101011 #
b101011 %
b1010101 !
1"
#432
0"
#433
b101010 #
b101010 %
b1010110 !
1"
#434
0"
#435
b101001 #
b101001 %
b1010111 !
1"
#436
0"
#437
b101000 #
b101000 %
b1011000 !
1"
#438
0"
#439
b100111 #
b100111 %
b1011001 !
1"
#440
0"
#441
b100110 #
b100110 %
b1011010 !
1"
#442
0"
#443
b100101 #
b100101 %
b1011011 !
1"
#444
0"
#445
b100100 #
b100100 %
b1011100 !
1"
#446
0"
#447
b100011 #
b100011 %
b1011101 !
1"
#448
0"
#449
b100010 #
b100010 %
b1011110 !
1"
#450
0"
#451
b100001 #
b100001 %
b1011111 !
1"
#452
0"
#453
b100000 #
b100000 %
b1100000 !
1"
#454
0"
#455
b11111 #
b11111 %
b1100001 !
1"
#456
0"
#457
b11110 #
b11110 %
b1100010 !
1"
#458
0"
#459
b11101 #
b11101 %
b1100011 !
1"
#460
0"
#461
b11100 #
b11100 %
b1100100 !
1"
#462
0"
#463
b11011 #
b11011 %
b1100101 !
1"
#464
0"
#465
b11010 #
b11010 %
b1100110 !
1"
#466
0"
#467
b11001 #
b11001 %
b1100111 !
1"
#468
0"
#469
b11000 #
b11000 %
b1101000 !
1"
#470
0"
#471
b10111 #
b10111 %
b1101001 !
1"
#472
0"
#473
b10110 #
b10110 %
b1101010 !
1"
#474
0"
#475
b10101 #
b10101 %
b1101011 !
1"
#476
0"
#477
b10100 #
b10100 %
b1101100 !
1"
#478
0"
#479
b10011 #
b10011 %
b1101101 !
1"
#480
0"
#481
b10010 #
b10010 %
b1101110 !
1"
#482
0"
#483
b10001 #
b10001 %
b1101111 !
1"
#484
0"
#485
b10000 #
b10000 %
b1110000 !
1"
#486
0"
#487
b1111 #
b1111 %
b1110001 !
1"
#488
0"
#489
b1110 #
b1110 %
b1110010 !
1"
#490
0"
#491
b1101 #
b1101 %
b1110011 !
1"
#492
0"
#493
b1100 #
b1100 %
b1110100 !
1"
#494
0"
#495
b1011 #
b1011 %
b1110101 !
1"
#496
0"
#497
b1010 #
b1010 %
b1110110 !
1"
#498
0"
#499
b1001 #
b1001 %
b1110111 !
1"
#500
0"
#501
b1000 #
b1000 %
b1111000 !
1"
#502
0"
#503
b111 #
b111 %
b1111001 !
1"
#504
0"
#505
b110 #
b110 %
b1111010 !
1"
#506
0"
#507
b101 #
b101 %
b1111011 !
1"
#508
0"
#509
b100 #
b100 %
b1111100 !
1"
#510
0"
#511
b11 #
b11 %
b1111101 !
1"
#512
0"
#513
b10 #
b10 %
b1111110 !
1"
#514
0"
#515
b1 #
b1 %
b1111111 !
1"
