lab4/instruction_decoder/instruction_decoder.v
module instruction_decoder (instruction, opcode, Rm, Rn, Rd, Rt, shamt, DT_address, op,BR_Address, COND_BR_address);

	input [31:0] instruction;
	output reg [10:0] opcode;
	output reg [4:0] Rm;
	output reg [4:0] Rn;
	output reg [4:0] Rd;
	output reg [4:0] Rt;
	output reg [4:0] shamt;
	output reg [7:0] DT_address;
	output reg [1:0] op;
	output reg [25:0] BR_Address;
	output reg [17:0] COND_BR_address;
	
	always @ (*) begin
		if (instruction[31:21]==11'h458) begin
			opcode = instruction [31:21];
			Rm = instruction [20:16];
			shamt = instruction [15:10];
			Rn= instruction [9:5];
			Rd = instruction [4:0];
		end
	
	end
	

endmodule

lab4/instruction_decoder/instruction_decoder_tb.v
`include "instruction_decoder.v"

module instruction_decoder_tb ();
	
	wire [31:0] instruction;
	wire [10:0] opcode;
	wire [4:0] Rm;
	wire [4:0] Rn;
	wire [4:0] Rd;
	wire [4:0] Rt;
	wire [4:0] shamt;
	wire [7:0] DT_address;
	wire [1:0] op;
	wire [25:0] BR_Address;
	wire [17:0] COND_BR_address;
	wire [10:0] ALUImm;
	
	instruction_decoder myDecoder (instruction, opcode, Rm, Rn, Rd, Rt, shamt, DT_address, op,BR_Address, COND_BR_address, ALUImm);
	instruction_decoder_Tester DecoderTester (instruction, opcode, Rm, Rn, Rd, Rt, shamt, DT_address, op,BR_Address, COND_BR_address, ALUImm);
	
	initial begin
		$dumpfile ("instruction_decoder.vcd");
		$dumpvars (0,DecoderTester);
	
	end
	
endmodule

module instruction_decoder_Tester (instruction, opcode, Rm, Rn, Rd, Rt, shamt, DT_address, op,BR_Address, COND_BR_address, ALUImm);
	output reg [31:0] instruction;
	input wire [10:0] opcode;
	input wire [4:0] Rm;
	input wire [4:0] Rn;
	input wire [4:0] Rd;
	input wire [4:0] Rt;
	input wire [4:0] shamt;
	input wire [7:0] DT_address;
	input wire [1:0] op;
	input wire [25:0] BR_Address;
	input wire [17:0] COND_BR_address;
	input wire [10:0] ALUImm;
	
	parameter stimDelay =1;
	
	integer i=0;
	
	initial begin
		$monitor ("instruction:%h opcode:%h Rm:%b Rn:%b Rd:%b Rt:%b shamt:%b DT_address:%d op:%b BR_Address:%d COND_BR_address:%d",instruction,opcode,Rm,Rn,Rd,Rt,shamt,DT_address,op,BR_Address,COND_BR_address);
	end
	
	initial begin
		#stimDelay;instruction=32'b10001011000000010001000011001000;
		#stimDelay; instruction=32'b10010001000000000001110000001001;i=i+1;//addi
		#stimDelay; instruction=32'b11111000000000000000001001101001;i=i+1;//stur
		#stimDelay; instruction=32'b11111000010000000000001001101001;i=i+1;//ldur
		#stimDelay; instruction=32'b11001011000010100000000100101011;i=i+1;//sub
		#stimDelay; instruction=32'b11101011000011000000000101100000;i=i+1;//subs
		#stimDelay; instruction=32'b01010100000000000000001010000000;i=i+1;//B.GT
		#stimDelay; instruction=32'b11010011011000000001010100101001;i=i+1;//LSL
		#stimDelay; instruction=32'b00010100000000000000000000011010;i=i+1;//b
		#stimDelay;
		#stimDelay;
		$finish;
	end
endmodule

lab4/instruction_decoder/instruction_decoder.vcd
$date
	Fri Mar 03 01:07:33 2017
$end
$version
	Icarus Verilog
$end
$timescale
	1s
$end
$scope module instruction_decoder_tb $end
$scope module DecoderTester $end
$var wire 5 ! shamt [4:0] $end
$var wire 11 " opcode [10:0] $end
$var wire 2 # op [1:0] $end
$var wire 5 $ Rt [4:0] $end
$var wire 5 % Rn [4:0] $end
$var wire 5 & Rm [4:0] $end
$var wire 5 ' Rd [4:0] $end
$var wire 8 ( DT_address [7:0] $end
$var wire 18 ) COND_BR_address [17:0] $end
$var wire 26 * BR_Address [25:0] $end
$var wire 11 + ALUImm [10:0] $end
$var reg 32 , instruction [31:0] $end
$var integer 32 - i [31:0] $end
$upscope $end
$upscope $end
$enddefinitions $end
#0
$dumpvars
b0 -
bx ,
bx +
bx *
bx )
bx (
bx '
bx &
bx %
bx $
bx #
bx "
bx !
$end
#1
b1000 '
b110 %
b100 !
b1 &
b10001011000 "
b10001011000000010001000011001000 ,
#2
b1001 '
b111 +
b0 %
b1001000100 "
b1 -
b10010001000000000001110000001001 ,
#3
b1001 $
b10011 %
b0 #
b0 (
b11111000000 "
b10 -
b11111000000000000000001001101001 ,
#4
b11111000010 "
b11 -
b11111000010000000000001001101001 ,
#5
b1011 '
b1001 %
b0 !
b1010 &
b11001011000 "
b100 -
b11001011000010100000000100101011 ,
#6
b0 '
b1011 %
b1100 &
b11101011000 "
b101 -
b11101011000011000000000101100000 ,
#7
b0 $
b10100 )
b1010100 "
b110 -
b1010100000000000000001010000000 ,
#8
b1001 '
b1001 %
b101 !
b0 &
b11010011011 "
b111 -
b11010011011000000001010100101001 ,
#9
b11010 *
b101 "
b1000 -
b10100000000000000000000011010 ,
