lab3/alu.v
module alu (outBus,Zero,Overflow,Carry,Negative,BusA,BusB,Control);

	output [31:0] outBus;
	output Zero,Overflow,Carry,Negative;
	input [31:0] BusA,BusB;
	input [2:0] Control;
	
	//And
	assign outBus= (Control==3'b011)? BusA&BusB:32'bZ;
	//Or
	assign outBus= (Control==3'b100)? BusA|BusB:32'bZ;
	//Xor
	assign outBus= (Control==3'b101)? BusA^BusB:32'bZ;
	//Left Shift
	assign outBus= (Control==3'b110)? BusA<<4:32'bZ;

	assign Zero=(outBus==1'b0)? 1'b1:1'b0;
	assign Negative=(outBus[31]==1'b1)? 1'b1:1'b0;
endmodule

//TESTING
/*
module testBench;
	wire [31:0] outBus;
	wire Zero,Overflow,Carry,Negative;
	wire [31:0] BusA,BusB;
	wire [2:0] Control;
	
	alu my_alu(outBus,Zero,Overflow,Carry,Negative,BusA,BusB,Control);
	
	Tester aTester(outBus,Zero,Overflow,Carry,Negative,BusA,BusB,Control);
	
	initial begin
		$dumpfile("alu.vcd");
		$dumpvars (1,my_alu);
	end
	
endmodule

module Tester (outBus,Zero,Overflow,Carry,Negative,BusA,BusB,Control);

	input wire [31:0] outBus;
	input wire Zero,Overflow,Carry,Negative;
	output reg [31:0] BusA,BusB;
	output reg [2:0] Control;
	
	parameter stimDelay = 1;
	
	initial
		begin
			//$display ("\t clk \t address \t data \t RW \t OE");
			$monitor ("\t BusA:%b \t\t BusB:%b \t\t OutBus:%b \t\t Control:%b ",BusA,BusB,outBus,Control);
		end
	
	initial
		begin
			#stimDelay; BusA=1'b0;BusB=1'b0;Control=3'b011;
			#stimDelay;
			#stimDelay;
			#stimDelay; BusA=4'b0110; BusB=4'b0100;
			#stimDelay;
			#stimDelay;BusA=4'b0110;BusB=4'b1001;Control= 3'b100;
			#stimDelay;
			#stimDelay;BusA=4'b1111; Control = 3'b101;
			#stimDelay;
			#stimDelay;Control = 3'b110;
			#stimDelay;
			#stimDelay;
			#stimDelay;Control = 3'b000;
			#stimDelay;
			#stimDelay;
			#stimDelay;
			#stimDelay;
		end
	
endmodule
*/

lab3/aluDemo.v
`include "alu.v"

module aluDemo (HEX0,HEX1,HEX2,HEX3,SW,KEY,clk);
	output [15:0] HEX0,HEX1,HEX2,HEX3;
	input [9:0] SW;
	input [1:0] KEY;
	input clk;
	
	reg [15:0] tHex0,tHex1,tHex2,tHex3;
	reg [2:0] Control,PrevControl;
	reg [31:0]BusA,BusB,TempBusA,TempBusB,TempOutBus;
	wire Overflow,Carry,Negative,Zero;
	wire [31:0] outBus;
	
	alu my_alu(outBus,Zero,Overflow,Carry,Negative,BusA,BusB,Control);
	
	initial begin
		tHex0=1'b0;
		tHex1=1'b0;
		tHex2=1'b0;
		tHex3=1'b0;
		Control=1'b0;
		BusA=1'b0;
		BusB=1'b0;
		TempBusA=1'b0;
		TempBusB=1'b0;
		TempOutBus=1'b0;
	end
	
	always @ (negedge clk) begin
		if (KEY[1]) begin
			TempOutBus=outBus;
		end
	end
	
	always @ (posedge clk) begin
		//Modify Temp Data
		if (SW[3]&&(SW[9:8]==1'b0)) TempBusA[31:16]=TempBusA[31:16]+1'b1;
		if (SW[2]&&(SW[9:8]==1'b0)) TempBusA[15:0]=TempBusA[15:0]+1'b1;
		if (SW[1]&&(SW[9:8]==1'b1)) TempBusB[31:16]=TempBusB[31:16]+1'b1;
		if (SW[0]&&(SW[9:8]==1'b1)) TempBusB[15:0]=TempBusB[15:0]+1'b1;
		
		//Load the input data into the alu
		if (KEY[0]&&(SW[9:8]==1'b0)) BusA=TempBusA;
		else if (KEY[0]&&(SW[9:8]==1'b1)) BusB=TempBusB;
		
		//Control Input
		if (KEY[1]) begin
			Control=SW[6:4];
			PrevControl=Control;
			
		end	
		else Control=1'b0;
		
		//Display
		if (SW[9]) begin
			tHex2=PrevControl;
			tHex3=SW[6:4];
			tHex1=TempOutBus[31:16];
			tHex0=TempOutBus[15:0];
		end
		else if (SW[8]) begin
			tHex3=TempBusB[31:16];
			tHex2=TempBusB[15:0];
			tHex1=BusB[31:16];
			tHex0=BusB[15:0];
		end
		else begin
			tHex3=TempBusA[31:16];
			tHex2=TempBusA[15:0];
			tHex1=BusA[31:16];
			tHex0=BusA[15:0];
		end

	end
	
	assign HEX0=tHex0;
	assign HEX1=tHex1;
	assign HEX2=tHex2;
	assign HEX3=tHex3;
	
endmodule


//TESTING
module testBench;

	wire [15:0] HEX0,HEX1,HEX2,HEX3;
	wire [9:0] SW;
	wire [1:0] KEY;
	wire clk;
	
	aluDemo my_aluDemo (HEX0,HEX1,HEX2,HEX3,SW,KEY,clk);
	Tester aTester (HEX0,HEX1,HEX2,HEX3,SW,KEY,clk);

	initial begin
		$dumpfile ("aluDemo.vcd");
		$dumpvars (1,my_aluDemo);
	end
	
endmodule

module Tester (HEX0,HEX1,HEX2,HEX3,SW,KEY,clk);

	input wire [15:0] HEX0,HEX1,HEX2,HEX3;
	output reg [9:0] SW;
	output reg [1:0] KEY;
	output reg clk;
	
	parameter stimDelay = 1;
	
	initial
		begin
			//$display ("\t clk \t address \t data \t RW \t OE");
			$monitor ("clk:%b\t HEX1:%b \t\t HEX0:%b \t\t HEX3:%b \t\t HEX2:%b \t KEY0:%b\t KEY1:%b",clk, HEX1,HEX0,HEX3,HEX2,KEY[0],KEY[1]);
		end
	
	integer i;
	
	initial
		begin
			#stimDelay; clk=1'b1; SW=1'b0; KEY=1'b0;
			#stimDelay; clk=1'b0;
			#stimDelay; clk=1'b1; SW[9:8]=1'b0; SW[3]=1'b1; 
			#stimDelay; clk=1'b0;
			#stimDelay; clk=1'b1; SW[3]=1'b0; SW[6:4]=3'b101; KEY[0]=1'b1;
			#stimDelay; clk=1'b0;
			#stimDelay; clk=1'b1; KEY[0]=1'b0; KEY[1]=1'b1;
			#stimDelay; clk=1'b0;
			#stimDelay; clk=1'b1; KEY[1]=1'b0;
			#stimDelay; clk=1'b0;
			#stimDelay; clk=1'b1; SW[9]=1'b1;
			#stimDelay; clk=1'b0;
			#stimDelay; clk=1'b1;
			#stimDelay; clk=1'b0;
			#stimDelay; clk=1'b1;
			#stimDelay; clk=1'b0;
			#stimDelay; clk=1'b1;
			#stimDelay; clk=1'b0;
			#stimDelay; clk=1'b1;SW[6:4]=1'b0;
			#stimDelay; clk=1'b0;
			#stimDelay; clk=1'b1;
			#stimDelay; clk=1'b0;
			#stimDelay; clk=1'b1;
			#stimDelay; clk=1'b0;
			#stimDelay; clk=1'b1;
			#stimDelay; clk=1'b0;
			#stimDelay; clk=1'b1;
			#stimDelay; clk=1'b0;
			#stimDelay; clk=1'b1;
			#stimDelay; clk=1'b0;
			#stimDelay; clk=1'b1;
			#stimDelay; clk=1'b0;
			#stimDelay; clk=1'b1;
			#stimDelay; clk=1'b0;
			#stimDelay; clk=1'b1;
			#stimDelay; clk=1'b0;
			#stimDelay; clk=1'b1;
			#stimDelay; clk=1'b0;
			#stimDelay; clk=1'b1;
			#stimDelay; clk=1'b0;
			#stimDelay; clk=1'b1;
			#stimDelay; clk=1'b0;
			#stimDelay; clk=1'b1;
			#stimDelay; clk=1'b0;
			#stimDelay; clk=1'b1;
			#stimDelay; clk=1'b0;
			#stimDelay; clk=1'b1;
			#stimDelay; clk=1'b0;
			#stimDelay; clk=1'b1;
			#stimDelay; clk=1'b0;
			#stimDelay; clk=1'b1;
			#stimDelay; clk=1'b0;
			#stimDelay; clk=1'b1;
			#stimDelay; clk=1'b0;
			#stimDelay; clk=1'b1;
			#stimDelay; clk=1'b0;
			#stimDelay; clk=1'b1;
			#stimDelay; clk=1'b0;
			#stimDelay; clk=1'b1;
			#stimDelay; clk=1'b0;
			#stimDelay; clk=1'b1;
			#stimDelay; clk=1'b0;

		end

endmodule

lab3/aluDemo.vcd
$date
	Thu Feb 09 21:53:19 2017
$end
$version
	Icarus Verilog
$end
$timescale
	1s
$end
$scope module testBench $end
$scope module my_aluDemo $end
$var wire 1 ! Carry $end
$var wire 16 " HEX0 [15:0] $end
$var wire 16 # HEX1 [15:0] $end
$var wire 16 $ HEX2 [15:0] $end
$var wire 16 % HEX3 [15:0] $end
$var wire 2 & KEY [1:0] $end
$var wire 1 ' Overflow $end
$var wire 10 ( SW [9:0] $end
$var wire 1 ) clk $end
$var wire 32 * outBus [31:0] $end
$var wire 1 + Zero $end
$var wire 1 , Negative $end
$var reg 32 - BusA [31:0] $end
$var reg 32 . BusB [31:0] $end
$var reg 3 / Control [2:0] $end
$var reg 3 0 PrevControl [2:0] $end
$var reg 32 1 TempBusA [31:0] $end
$var reg 32 2 TempBusB [31:0] $end
$var reg 32 3 TempOutBus [31:0] $end
$var reg 16 4 tHex0 [15:0] $end
$var reg 16 5 tHex1 [15:0] $end
$var reg 16 6 tHex2 [15:0] $end
$var reg 16 7 tHex3 [15:0] $end
$upscope $end
$upscope $end
$enddefinitions $end
#0
$dumpvars
b0 7
b0 6
b0 5
b0 4
b0 3
b0 2
b0 1
bx 0
b0 /
b0 .
b0 -
x,
x+
bz *
x)
bx (
z'
bx &
b0 %
b0 $
b0 #
b0 "
z!
$end
#1
b0 &
b0 (
1)
#2
0)
#3
b1 %
b1 7
b10000000000000000 1
b1000 (
1)
#4
0)
#5
b1 #
b1 5
b10000000000000000 -
b1 &
b1010000 (
1)
#6
0)
#7
0,
0+
b10000000000000000 *
b101 0
b101 /
b10 &
1)
#8
b10000000000000000 3
0)
#9
x,
x+
bz *
b0 /
b0 &
1)
#10
0)
#11
b101 %
b101 7
b101 $
b101 6
b1001010000 (
1)
#12
0)
#13
1)
#14
0)
#15
1)
#16
0)
#17
1)
#18
0)
#19
b0 %
b0 7
b1000000000 (
1)
